{
    "code": "SCP-548",
    "title": "\"Buz Örümceği\"",
    "text": "\"SCP-548 yetişkin aşamaya geçişte \n Madde No: SCP-548 \n Nesne Sınıfı: Euclid \n Özel Saklama Prosedürleri: SCP-548, 50 cm x 50 cm'lik bir teraryumda 24°C'de tutulmalıdır. Muhafaza alanı, yüksek termal şok direncine sahip modifiye edilmiş borosilikat camdan veya 50°C'den büyük ani sıcaklık değişimleriyle kırılgan hale gelmeyen diğer malzemelerden oluşmalıdır. SCP-548'in teraryum duvarlarını aşındırmak için aktif bir girişimde bulunması durumunda, muhafaza alanı derhal 500 mL sıvı nitrojen ile doldurulmalı ve denek geçici olarak güçlendirilmiş çelik bir teraryuma alınmalıdır. Denek her dört günde bir fare ile beslenmelidir. \n SCP-548, test için gerekli olmadıkça ellenmemelidir. Bakıcılar, tarantula davranışlarına en azından yüzeysel olarak aşina olmalı ve ağır yalıtımlı eldivenler giymelidir. Denek herhangi bir agresif davranış sergilerse, ellemeyi derhal durdurun. Isırılması durumunda personel derhal hipotermi ve donma için tedavi edilmelidir. Şiddetli ısırıklar için ısıtılmış sıvılarla aktif intratorasik ısınma endikedir. \n Açıklama: SCP-548, 7,3 cm uzunluğunda dişi bir kobalt tarantuladır (Cyriopagopus lividus). Zehri, canlı doku ile temas ettiğinde son derece endotermik bir reaksiyona girer; 0,5 mL'den az zehir enjekte eden tek bir ısırık, etkilenen bölgede ortalama 38°C'lik bir sıcaklık düşüşüne neden olur. Bir ısırık bir insanda bölgesel donmaya neden olmak için yeterlidir ve zehrin merkezi dolaşım sistemine ulaşması durumunda ölümcül bile olabilir. SCP-548'den küçük kurbanlar genellikle tamamen donar. \n SCP-548'in beslenme yapıları, son derece sert ve tırtıklı olan maksillalar dışında, türünün bir örümceği için normaldir. Zehirli bir ısırık vererek ve ardından avı soğurken güvenli bir yere sürükleyerek beslenir. İnzivadayken, avın hala donmuş olan dokusunu yenilebilir parçalara ayırmaya devam eder. Bu beslenme tarzı alışılmadık bir ağız parçası gücü gerektirir. \n Ek: SCP-548, çoğu Cyriopagopus türü gibi genellikle insanlarla temastan kaçınır. Ancak köşeye sıkıştırılırsa hızla saldırganlaşır ve kaçmadan önce algıladığı saldırganı ısırmaya çalışır. \n Nesne, belirgin bir olumsuz etki olmaksızın tamamen dondurulabilir. Defalarca dondurulmuş, her seferinde çözüldüğünde normal davranışına devam etmiştir. Bu direncin mekanizmasını saptamak ve uzun süreli depolama için uygunluğunu belirlemek için daha fazla araştırma yapılması gerekmektedir. \n Ek 2: Tarihsel olarak SCP-2082'den sorumlu olan aynı anomalik etkinin şimdi SCP-548'i etkiliyor olması muhtemeldir. Bu bağlantıya yönelik araştırma, Olay 2082-Prime'ın ardından korunan SCP-2082 doku örnekleri kullanılarak şu anda devam etmektedir. Canlı bir örnek kullanımı için SCP-2082 klonlama programının yeniden başlatılmasına yönelik öneriler reddedilmiştir. \n « SCP-547 | SCP-548 | SCP-549 » \n Bu sayfaya şu şekilde atıf yapın: \n SCP Wiki'den Photosynthetic ve Dr_Fences tarafından \"SCP-548\". Kaynak: https://scp-wiki.wikidot.com/scp-548. CC-BY-SA kapsamında lisanslanmıştır. \n Daha fazla bilgi için Lisanslama Kılavuzu'na bakın.\nLisanslama Açıklamaları \n Dosya Adı: 546.jpg\nAd: Dosya:Haplopelma lividum.jpg\nYazar: Dávid Horváth \n Lisans: CC BY 2.0\nKaynak: https://commons.wikimedia.org/wiki/File:Haplopelma_lividum.jpg\nNotlar: Bu çalışma Dr_Fences tarafından SCP-548'in bir türevidir, CC BY-SA 3.0. \n Wiki içi içerik hakkında daha fazla bilgi için Lisanslama Ana Listesini ziyaret edin.\"",
    "image captions": "https://scp-wiki.wdfiles.com/local--files/scp-548/scp-548.jpg",
    "rating": "+76",
    "state": "aktif",
    "tags": "_cc _licensebox canlı örümceğimsi euclid omurgasız yeniden-yazım scp",
    "link": "https://scp-wiki.wikidot.com/scp-548"
}